pymms/__init__.py
pymms/_version.py
pymms/config_template.ini
pymms/data/__init__.py
pymms/data/anc.py
pymms/data/dss.py
pymms/data/edi.py
pymms/data/edp.py
pymms/data/epd.py
pymms/data/fgm.py
pymms/data/fpi.py
pymms/data/fsm.py
pymms/data/hapgood.py
pymms/data/maxlut.py
pymms/data/scm.py
pymms/data/util.py
pymms/sdc/__init__.py
pymms/sdc/mrmms_sdc_api.py
pymms/sdc/sdc_login.py
pymms/sdc/selections.py
pymms/sql/__init__.py
pymms/sql/data_export.py
pymms/sql/data_export_sql.py
pymms/sql/server_funcs_consolidated.py
pymms/sql/server_funcs_consolidated_bucket.py
pymms/sql/sql_funcs.py
pymms/util/__init__.py
pymms/util/config.py
pymms/util/tai.py
nasa_pymms-0.4.8.dist-info/LICENSE.rst
nasa_pymms-0.4.8.dist-info/METADATA
nasa_pymms-0.4.8.dist-info/WHEEL
nasa_pymms-0.4.8.dist-info/entry_points.txt
nasa_pymms-0.4.8.dist-info/top_level.txt
nasa_pymms-0.4.8.dist-info/RECORD
