Metadata-Version: 2.1
Name: nasa-pymms
Version: 0.4.8
Summary: Access data from the MMS mission via its API.
Home-page: https://github.com/argallmr/pymms
Author: Matthew R. Argall
Author-email: argallmr@gmail.com
License: MIT
Keywords: physics space-physics MMS
Classifier: Programming Language :: Python :: 3
Classifier: Operating System :: OS Independent
Classifier: License :: OSI Approved :: MIT License
Classifier: Development Status :: 4 - Beta
Classifier: Topic :: Scientific/Engineering :: Physics
Classifier: Topic :: Scientific/Engineering :: Astronomy
Classifier: Intended Audience :: Science/Research
Classifier: Natural Language :: English
Requires-Python: >=3.6
License-File: LICENSE.rst
Requires-Dist: numpy (>=1.24)
Requires-Dist: requests (>=2.22.0)
Requires-Dist: scipy (>=1.4.1)
Requires-Dist: tqdm (>=4.36.1)
Requires-Dist: cdflib (>=1.0.0)
Requires-Dist: matplotlib (>=3.4)
Provides-Extra: data
Requires-Dist: cdflib (>=0.3.18) ; extra == 'data'
Requires-Dist: xarray (>=0.16.0) ; extra == 'data'
Provides-Extra: gls
Requires-Dist: tensorflow (<=1.15,>=1.13.1) ; extra == 'gls'
Requires-Dist: keras (<=2.3.1,>=2.2.4) ; extra == 'gls'
Provides-Extra: sql
